<?xml version="1.0" encoding="utf-8" ?>
<Defs>

	<ThingDef ParentName="AnimalThingBase">
		<defName>O21_Goomba</defName>
		<label>goomba</label>
		<description>Goombas resemble small brown mushrooms, I have no idea how they're a threat, they just are...</description>
        <statBases>
            <PsychicSensitivity>0.5</PsychicSensitivity>
            <ToxicSensitivity>0</ToxicSensitivity>
            <Flammability>0</Flammability>
            <ComfyTemperatureMin>-100</ComfyTemperatureMin>
            <ComfyTemperatureMax>250</ComfyTemperatureMax>
        </statBases>
        <race>
            <needsRest>false</needsRest>
            <hasGenders>false</hasGenders>
            <foodType>None</foodType>
			<body>Human</body>
            <intelligence>ToolUser</intelligence>
            <thinkTreeMain>Mechanoid</thinkTreeMain>
            <baseBodySize>0.5</baseBodySize>
			<baseHealthScale>0.5</baseHealthScale>

            <lifeStageAges>
                <li>
                    <def>MechanoidFullyFormed</def>
                    <minAge>0</minAge>
                </li>
            </lifeStageAges>

			<soundMeleeHitPawn>Pawn_Melee_Punch_HitPawn</soundMeleeHitPawn>
			<soundMeleeHitBuilding>Pawn_Melee_Punch_HitBuilding</soundMeleeHitBuilding>
			<soundMeleeMiss>Pawn_Melee_Punch_Miss</soundMeleeMiss>
        </race>
        <butcherProducts>
            <Cloth>10</Cloth>
            <Steel>5</Steel>
            <WoodLog>3</WoodLog>
        </butcherProducts>
        <receivesSignals>true</receivesSignals>
		<tools>
			<li>
				<label>head</label>
				<capacities>
					<li>Blunt</li>
				</capacities>
				<power>10</power>
				<cooldownTime>2</cooldownTime>
				<linkedBodyPartsGroup>HeadAttackTool</linkedBodyPartsGroup>
				<ensureLinkedBodyPartsGroupAlwaysUsable>true</ensureLinkedBodyPartsGroupAlwaysUsable>
				<chanceFactor>0.2</chanceFactor>
			</li>
		</tools>
	</ThingDef>

    <PawnKindDef Name="GoombaBase" Abstract="True">
        <label>goomba</label>
        <race>O21_Goomba</race>
        <combatPower>60</combatPower>

        <defaultFactionType>O21_ShyGuys</defaultFactionType>
        <aiAvoidCover>true</aiAvoidCover>
        <destroyGearOnDrop>false</destroyGearOnDrop>
    </PawnKindDef>

    <PawnKindDef ParentName="GoombaBase">
        <defName>O21_Goomba</defName>
        <lifeStages>
            <li>
                <bodyGraphicData>
                    <texPath>Pawn/Goomba/goomba</texPath>
                    <graphicClass>Graphic_Multi</graphicClass>
                    <shaderType>CutoutComplex</shaderType>
                    <drawSize>1.0</drawSize>
                    <shadowData>
                        <volume>(0.4, 0.8, 0.4)</volume>
                    </shadowData>
                    <color>(140, 102, 73)</color>
                </bodyGraphicData>
            </li>
        </lifeStages>
    </PawnKindDef>

    <PawnKindDef ParentName="GoombaBase">
        <defName>O21_GoombaM</defName>
        <lifeStages>
            <li>
                <bodyGraphicData>
                    <texPath>Pawn/Goomba/goombaM</texPath>
                    <graphicClass>Graphic_Multi</graphicClass>
                    <shaderType>CutoutComplex</shaderType>
                    <drawSize>1.0</drawSize>
                    <shadowData>
                        <volume>(0.4, 0.8, 0.4)</volume>
                    </shadowData>
                    <color>(140, 102, 73)</color>
                </bodyGraphicData>
            </li>
        </lifeStages>
    </PawnKindDef>

    <PawnKindDef ParentName="GoombaBase">
        <defName>O21_GoombaPara</defName>
        <lifeStages>
            <li>
                <bodyGraphicData>
                    <texPath>Pawn/Goomba/goombapara</texPath>
                    <graphicClass>Graphic_Multi</graphicClass>
                    <shaderType>CutoutComplex</shaderType>
                    <drawSize>1.0</drawSize>
                    <shadowData>
                        <volume>(0.4, 0.8, 0.4)</volume>
                    </shadowData>
                    <color>(224, 209, 121)</color>
                </bodyGraphicData>
            </li>
        </lifeStages>
    </PawnKindDef>

    <PawnKindDef ParentName="GoombaBase">
        <defName>O21_GoombaParaM</defName>
        <lifeStages>
            <li>
                <bodyGraphicData>
                    <texPath>Pawn/Goomba/goombaparaM</texPath>
                    <graphicClass>Graphic_Multi</graphicClass>
                    <shaderType>CutoutComplex</shaderType>
                    <drawSize>1.0</drawSize>
                    <shadowData>
                        <volume>(0.4, 0.8, 0.4)</volume>
                    </shadowData>
                    <color>(224, 209, 121)</color>
                </bodyGraphicData>
            </li>
        </lifeStages>
    </PawnKindDef>

    <PawnKindDef ParentName="GoombaBase">
        <defName>O21_GoombaPirate</defName>
        <lifeStages>
            <li>
                <bodyGraphicData>
                    <texPath>Pawn/Goomba/goombapirate</texPath>
                    <graphicClass>Graphic_Multi</graphicClass>
                    <shaderType>CutoutComplex</shaderType>
                    <drawSize>1.0</drawSize>
                    <shadowData>
                        <volume>(0.4, 0.8, 0.4)</volume>
                    </shadowData>
                    <color>(140, 102, 73)</color>
                    <colorTwo>(150, 112, 196)</colorTwo>
                </bodyGraphicData>
            </li>
        </lifeStages>
    </PawnKindDef>

    <PawnKindDef ParentName="GoombaBase">
        <defName>O21_GoombaPirateM</defName>
        <lifeStages>
            <li>
                <bodyGraphicData>
                    <texPath>Pawn/Goomba/goombapirateM</texPath>
                    <graphicClass>Graphic_Multi</graphicClass>
                    <shaderType>CutoutComplex</shaderType>
                    <drawSize>1.0</drawSize>
                    <shadowData>
                        <volume>(0.4, 0.8, 0.4)</volume>
                    </shadowData>
                    <color>(140, 102, 73)</color>
                    <colorTwo>(150, 112, 196)</colorTwo>
                </bodyGraphicData>
            </li>
        </lifeStages>
    </PawnKindDef>

</Defs>